fgqled/__init__.py
fgqled/colors.py
fgqled/figfuncs.py
fgqled/plotter.py
fgqled/reader.py
fGQLED-0.17.1.dist-info/LICENSE
fGQLED-0.17.1.dist-info/METADATA
fGQLED-0.17.1.dist-info/WHEEL
fGQLED-0.17.1.dist-info/top_level.txt
fGQLED-0.17.1.dist-info/RECORD
