Metadata-Version: 2.1
Name: fGQLED
Version: 0.17.1
Summary: Standard functions used for the QDLED Project at ETH.
Home-page: UNKNOWN
Author: Killian Keller
Author-email: kkeller@ethz.ch
License: UNKNOWN
Platform: UNKNOWN
Classifier: Programming Language :: Python :: 3
Classifier: License :: OSI Approved :: MIT License
Classifier: Operating System :: OS Independent
